quicktune/__init__.py
quicktune/finetune/__init__.py
quicktune/finetune/finetune.py
quicktune/finetune/utils/__init__.py
quicktune/finetune/utils/available_models.py
quicktune/finetune/utils/build_parser.py
quicktune/finetune/utils/compute_embeddings.py
quicktune/finetune/utils/eval_autofinetune.py
quicktune/finetune/utils/finetuning_stategies.py
quicktune/finetune/utils/stoch_norm.py
quicktune/finetune/utils/train.py
quicktune/finetune/utils/utils.py
quicktune/finetune/utils/validate.py
quicktune/optimizers/__init__.py
quicktune/optimizers/bo.py
quicktune/optimizers/dyhpo.py
quicktune/optimizers/gp.py
quicktune/optimizers/quicktune.py
quicktune/tools/__init__.py
quicktune/tools/metadataset.py
quicktune/tools/searchspace.py
quicktune/tools/searchspaces/search_space_v1.yml
quicktune/tools/searchspaces/search_space_v2.yml
quicktune/tools/searchspaces/search_space_v3.yml
quicktune/tools/searchspaces/search_space_v4.yml
quicktune/tools/searchspaces/search_space_v5.yml
quicktune/tools/searchspaces/search_space_v6.yml
quicktune/tools/searchspaces/search_space_v7.yml
quicktune/tools/searchspaces/search_space_v8.yml
quicktune-0.0.4.dist-info/LICENSE
quicktune-0.0.4.dist-info/METADATA
quicktune-0.0.4.dist-info/WHEEL
quicktune-0.0.4.dist-info/top_level.txt
quicktune-0.0.4.dist-info/RECORD
