Metadata-Version: 2.1
Name: quicktune
Version: 0.0.4
Summary: Quick-Tune: Quickly Learning Which Pretrained Model to Finetune and How
Author-email: Ivo Rapant <rapanti@cs.uni-freiburg.de>
License: BSD 3-Clause License
Project-URL: Homepage, https://github.com/rapanti/quicktune
Classifier: Intended Audience :: Science/Research
Classifier: Intended Audience :: Developers
Classifier: License :: OSI Approved :: BSD License
Classifier: Programming Language :: Python
Classifier: Topic :: Software Development
Classifier: Topic :: Scientific/Engineering
Classifier: Operating System :: POSIX
Classifier: Operating System :: Unix
Classifier: Programming Language :: Python :: 3
Requires-Python: >=3.9
License-File: LICENSE
Requires-Dist: torch <2,>=1.12.1
Requires-Dist: torchvision >=0.13.1
Requires-Dist: torchaudio >=0.12.1
Requires-Dist: ConfigSpace
Requires-Dist: gpytorch
Requires-Dist: pandas
Requires-Dist: pyyaml
Requires-Dist: scikit-learn
Requires-Dist: tqdm
